py4jps/JPSGateway.py
py4jps/__init__.py
py4jps/agentlogging/__init__.py
py4jps/agentlogging/logging.conf
py4jps/agentlogging/logging.py
py4jps/resRegistry/__init__.py
py4jps/resRegistry/resManager.py
py4jps/resRegistry/resRegistry.py
py4jps/resources/__init__.py
py4jps/resources/resources_registry.json
py4jps/resources/JpsBaseLib/JpsBaseLib.py
py4jps/resources/JpsBaseLib/__init__.py
py4jps/resources/JpsBaseLib/info.txt
py4jps/resources/JpsBaseLib/jps-base-lib.jar
py4jps/resources/JpsBaseLib/lib/aopalliance-1.0.jar
py4jps/resources/JpsBaseLib/lib/apache-jena-libs-4.5.0.pom
py4jps/resources/JpsBaseLib/lib/bigdata-cache-2.1.4.jar
py4jps/resources/JpsBaseLib/lib/bigdata-client-2.1.4.jar
py4jps/resources/JpsBaseLib/lib/bigdata-common-util-2.1.4.jar
py4jps/resources/JpsBaseLib/lib/bigdata-core-2.1.4.jar
py4jps/resources/JpsBaseLib/lib/bigdata-ganglia-2.1.4.jar
py4jps/resources/JpsBaseLib/lib/bigdata-gas-2.1.4.jar
py4jps/resources/JpsBaseLib/lib/bigdata-statics-2.1.4.jar
py4jps/resources/JpsBaseLib/lib/bigdata-util-2.1.4.jar
py4jps/resources/JpsBaseLib/lib/caffeine-2.3.5.jar
py4jps/resources/JpsBaseLib/lib/checker-qual-3.5.0.jar
py4jps/resources/JpsBaseLib/lib/collection-0.7.jar
py4jps/resources/JpsBaseLib/lib/colt-2.1.4.jar
py4jps/resources/JpsBaseLib/lib/commons-beanutils-1.9.3.jar
py4jps/resources/JpsBaseLib/lib/commons-beanutils-core-1.8.0.jar
py4jps/resources/JpsBaseLib/lib/commons-cli-1.5.0.jar
py4jps/resources/JpsBaseLib/lib/commons-codec-1.15.jar
py4jps/resources/JpsBaseLib/lib/commons-collections-3.2.2.jar
py4jps/resources/JpsBaseLib/lib/commons-compress-1.21.jar
py4jps/resources/JpsBaseLib/lib/commons-configuration-1.6.jar
py4jps/resources/JpsBaseLib/lib/commons-csv-1.9.0.jar
py4jps/resources/JpsBaseLib/lib/commons-dbcp-1.3.jar
py4jps/resources/JpsBaseLib/lib/commons-digester-2.1.jar
py4jps/resources/JpsBaseLib/lib/commons-fileupload-1.3.1.jar
py4jps/resources/JpsBaseLib/lib/commons-httpclient-3.1.jar
py4jps/resources/JpsBaseLib/lib/commons-io-2.11.0.jar
py4jps-1.0.38.dist-info/LICENSE
py4jps-1.0.38.dist-info/METADATA
py4jps-1.0.38.dist-info/WHEEL
py4jps-1.0.38.dist-info/entry_points.txt
py4jps-1.0.38.dist-info/top_level.txt
py4jps-1.0.38.dist-info/RECORD
