Metadata-Version: 2.1
Name: py4jps
Version: 1.0.38
Summary: Py4jps is a thin Python wrapper for the TheWorldAvatar project.
Home-page: https://github.com/cambridge-cares/TheWorldAvatar/tree/develop/JPS_BASE_LIB/python_wrapper
Author: Daniel Nurkowski
Author-email: danieln@cmclinnovations.com
License: MIT
Classifier: License :: OSI Approved :: MIT License
Classifier: Development Status :: 4 - Beta
Classifier: Programming Language :: Python :: 3.5
Classifier: Programming Language :: Python :: 3.6
Classifier: Programming Language :: Python :: 3.7
Classifier: Programming Language :: Python :: 3.8
Classifier: Programming Language :: Python :: 3.9
Requires-Python: >=3.5
License-File: LICENSE
Requires-Dist: py4j (==0.10.9.1)
Requires-Dist: docopt
Requires-Dist: concurrent-log-handler
